abv/__init__.py
abv/address_book.py
abv/calculator.py
abv/files_sort.py
abv/main.py
abv/note_book.py
abv-1.0.0.dist-info/LICENSE
abv-1.0.0.dist-info/METADATA
abv-1.0.0.dist-info/WHEEL
abv-1.0.0.dist-info/entry_points.txt
abv-1.0.0.dist-info/top_level.txt
abv-1.0.0.dist-info/RECORD
