Metadata-Version: 2.1
Name: abv
Version: 1.0.0
Summary: Very helpful assistant bot
Home-page: https://github.com/VadimTrubay/abv.git
Author: Trubay_Vadim
Author-email: vadnetvadnet@ukr.net
License: MIT
License-File: LICENSE
Requires-Dist: numexpr
